preprocessing_ninja.py
PreProcessingNinja-0.0.1.dist-info/LICENSE
PreProcessingNinja-0.0.1.dist-info/METADATA
PreProcessingNinja-0.0.1.dist-info/WHEEL
PreProcessingNinja-0.0.1.dist-info/top_level.txt
PreProcessingNinja-0.0.1.dist-info/RECORD
