Metadata-Version: 2.1
Name: PreProcessingNinja
Version: 0.0.1
Summary: A data preprocessing helper consists of your basic preprocessing needs
Home-page: https://github.com/Bijoy99roy/PreProcessingNinja
Author: Bijoy Kumar Roy
License: UNKNOWN
Keywords: preprocessing,preprocessing ninja
Platform: UNKNOWN
Classifier: Programming Language :: Python :: 3
Classifier: License :: OSI Approved :: MIT License
Classifier: Operating System :: OS Independent
Requires-Python: >=3.6
Requires-Dist: scikit-learn
